BUGS
dnsflash.py
dnsomatic.conf.sample
dnsomatic_api.py
ez_setup.py
setup.py
DNSFlash.egg-info/PKG-INFO
DNSFlash.egg-info/SOURCES.txt
DNSFlash.egg-info/dependency_links.txt
DNSFlash.egg-info/entry_points.txt
DNSFlash.egg-info/top_level.txt
DNSFlash.egg-info/zip-safe
dist/DNS-O-Matic-0.20.tar.gz
dist/DNS_O_Matic-0.20-py2.5.egg