Metadata-Version: 1.0
Name: DNSFlash
Version: 0.3.1
Summary: Update IP on the DNS-O-Matic service
Home-page: http://www.sukkology.net
Author: SukkoPera
Author-email: software@sukkology.net
License: GPLv2
Keywords: dnsomatic opendns cjb dyndns
Platform: UNKNOWN
